contek_timbersaw/__init__.py
contek_timbersaw/async_compressor.py
contek_timbersaw/deleter.py
contek_timbersaw/timed_rolling_file_handler.py
contek_timbersaw-2.7.dist-info/LICENSE.txt
contek_timbersaw-2.7.dist-info/METADATA
contek_timbersaw-2.7.dist-info/WHEEL
contek_timbersaw-2.7.dist-info/top_level.txt
contek_timbersaw-2.7.dist-info/zip-safe
contek_timbersaw-2.7.dist-info/RECORD
