Metadata-Version: 2.1
Name: contek-timbersaw
Version: 2.7
Summary: Timbersaw for automatic logging configuration
Home-page: https://github.com/contek-io/contek-timbersaw
Author: contek_bjy
Author-email: bjy@contek.io
License: MIT
Platform: UNKNOWN
Classifier: Programming Language :: Python :: 3
Classifier: License :: OSI Approved :: MIT License
Classifier: Operating System :: OS Independent
Requires-Python: >=3.10
License-File: LICENSE.txt
